plotmanager/__init__.py
plotmanager/__main__.py
plotmanager/library/__init__.py
plotmanager/library/commands/__init__.py
plotmanager/library/commands/plots.py
plotmanager/library/parse/__init__.py
plotmanager/library/parse/configuration.py
plotmanager/library/utilities/__init__.py
plotmanager/library/utilities/commands.py
plotmanager/library/utilities/exceptions.py
plotmanager/library/utilities/jobs.py
plotmanager/library/utilities/log.py
plotmanager/library/utilities/notifications.py
plotmanager/library/utilities/objects.py
plotmanager/library/utilities/print.py
plotmanager/library/utilities/processes.py
chia_plot_manager-1.0.1.dist-info/LICENSE
chia_plot_manager-1.0.1.dist-info/METADATA
chia_plot_manager-1.0.1.dist-info/WHEEL
chia_plot_manager-1.0.1.dist-info/entry_points.txt
chia_plot_manager-1.0.1.dist-info/top_level.txt
chia_plot_manager-1.0.1.dist-info/RECORD
